{"MODEL": "Random Forest", "SITE": "bnz", "SRS_CHAMBER": "FD01_flux", "FEATURES": ["st2", "le", "pres", "h", "rad", "airt", "ppt.roll", "rh", "vpd", "ws"], "RSQUARE": 0.784, "SLOPE": 1.083, "RMSE": 0.7347650666871359, "N_RMSE": 0.34723280859842454, "MAE": 0.49968455622019736, "start_t": "2016-01-01 00:00:00", "end_t": "2023-12-31 23:00:00", "n_filled": 50946, "n_observed": 19182, "n_obs_spring": 6104, "n_obs_summer": 8275, "n_obs_autumn": 4614, "n_obs_winter": 189, "n_filled_spring": 11560, "n_filled_summer": 9389, "n_filled_autumn": 12858, "n_filled_winter": 17139}